ue4docker/__init__.py
ue4docker/__main__.py
ue4docker/build.py
ue4docker/clean.py
ue4docker/diagnostics_cmd.py
ue4docker/export.py
ue4docker/info.py
ue4docker/main.py
ue4docker/setup_cmd.py
ue4docker/test.py
ue4docker/version.py
ue4docker/version_cmd.py
ue4docker/diagnostics/__init__.py
ue4docker/diagnostics/base.py
ue4docker/diagnostics/diagnostic_20gig.py
ue4docker/diagnostics/diagnostic_8gig.py
ue4docker/diagnostics/diagnostic_all.py
ue4docker/diagnostics/diagnostic_network.py
ue4docker/dockerfiles/diagnostics/20gig/windows/Dockerfile
ue4docker/dockerfiles/diagnostics/8gig/linux/Dockerfile
ue4docker/dockerfiles/diagnostics/8gig/windows/Dockerfile
ue4docker/dockerfiles/diagnostics/8gig/windows/test.ps1
ue4docker/dockerfiles/diagnostics/network/linux/Dockerfile
ue4docker/dockerfiles/diagnostics/network/windows/Dockerfile
ue4docker/dockerfiles/ue4-build-prerequisites/linux/Dockerfile
ue4docker/dockerfiles/ue4-build-prerequisites/windows/.dockerignore
ue4docker/dockerfiles/ue4-build-prerequisites/windows/Dockerfile
ue4docker/dockerfiles/ue4-build-prerequisites/windows/buildtools-exitcode.py
ue4docker/dockerfiles/ue4-build-prerequisites/windows/install-prerequisites.bat
ue4docker/dockerfiles/ue4-build-prerequisites/windows/remove-duplicate-dlls.ps1
ue4docker/dockerfiles/ue4-engine/linux/Dockerfile
ue4docker/dockerfiles/ue4-engine/windows/Dockerfile
ue4docker/dockerfiles/ue4-full/linux/Dockerfile
ue4docker/dockerfiles/ue4-full/linux/pulseaudio-client.conf
ue4docker/dockerfiles/ue4-full/windows/Dockerfile
ue4docker/dockerfiles/ue4-minimal/linux/.dockerignore
ue4docker/dockerfiles/ue4-minimal/linux/Dockerfile
ue4docker/dockerfiles/ue4-minimal/linux/copy-toolchain.py
ue4docker/dockerfiles/ue4-minimal/linux/enable-opengl.py
ue4docker/dockerfiles/ue4-minimal/linux/fix-targets.py
ue4docker/dockerfiles/ue4-minimal/linux/patch-build-graph.py
ue4docker/dockerfiles/ue4-minimal/linux/patch-filters-xml.py
ue4docker/dockerfiles/ue4-minimal/linux/set-changelist.py
demo_ue4_docker-0.0.104.dist-info/LICENSE
demo_ue4_docker-0.0.104.dist-info/METADATA
demo_ue4_docker-0.0.104.dist-info/WHEEL
demo_ue4_docker-0.0.104.dist-info/entry_points.txt
demo_ue4_docker-0.0.104.dist-info/top_level.txt
demo_ue4_docker-0.0.104.dist-info/RECORD
