Metadata-Version: 2.1
Name: demo-ue4-docker
Version: 0.0.104
Summary: Windows and Linux containers for Unreal Engine 4
Home-page: https://github.com/Singaravelu-web/Unreal-Demo2
Author: Velu Jay
Author-email: velujay@gmail.com
License: MIT
Keywords: epic unreal engine docker
Classifier: License :: OSI Approved :: MIT License
Classifier: Programming Language :: Python :: 3.6
Classifier: Programming Language :: Python :: 3.7
Classifier: Programming Language :: Python :: 3.8
Classifier: Programming Language :: Python :: 3.9
Classifier: Programming Language :: Python :: 3.10
Classifier: Topic :: Software Development :: Build Tools
Classifier: Environment :: Console
Requires-Python: >=3.6
License-File: LICENSE
Requires-Dist: colorama
Requires-Dist: container-utils
Requires-Dist: docker (>=3.0.0)
Requires-Dist: humanfriendly
Requires-Dist: Jinja2 (>=2.11.3)
Requires-Dist: packaging (>=19.1)
Requires-Dist: psutil
Requires-Dist: requests
Requires-Dist: semver (<3.0.0,>=2.7.9)
Requires-Dist: termcolor
Requires-Dist: twine (>=1.11.0)
Requires-Dist: wheel (>=0.31.0)
Requires-Dist: setuptools (>=60.4.0) ; python_version >= "3.7.0"
